trk/__init__.py
trk/__main__.py
trk/cli.py
trk/config.py
trk/controller.py
trk/database.py
trk/output.py
trk-0.1.8.dist-info/entry_points.txt
trk-0.1.8.dist-info/WHEEL
trk-0.1.8.dist-info/METADATA
trk-0.1.8.dist-info/RECORD
